logillm/__init__.py
logillm/py.typed
logillm/core/__init__.py
logillm/core/assertions.py
logillm/core/avatar.py
logillm/core/callback_mixin.py
logillm/core/callbacks.py
logillm/core/config_utils.py
logillm/core/demos.py
logillm/core/embedders.py
logillm/core/extractors.py
logillm/core/format_adapters.py
logillm/core/hyperparameters.py
logillm/core/jsonl_callback.py
logillm/core/jsonl_logger.py
logillm/core/knn.py
logillm/core/module_extensions.py
logillm/core/modules.py
logillm/core/optimizers.py
logillm/core/parameters.py
logillm/core/persistence.py
logillm/core/predict.py
logillm/core/providers.py
logillm/core/react.py
logillm/core/refine.py
logillm/core/retry.py
logillm/core/tools.py
logillm/core/types.py
logillm/core/usage_tracker.py
logillm/core/adapters/__init__.py
logillm/core/adapters/base.py
logillm/core/adapters/chain.py
logillm/core/adapters/chat.py
logillm/core/adapters/json_adapter.py
logillm/core/adapters/markdown.py
logillm/core/adapters/text.py
logillm/core/adapters/utils.py
logillm/core/adapters/xml.py
logillm/core/signatures/__init__.py
logillm/core/signatures/base.py
logillm/core/signatures/factory.py
logillm/core/signatures/fields.py
logillm/core/signatures/parser.py
logillm/core/signatures/signature.py
logillm/core/signatures/spec.py
logillm/core/signatures/types.py
logillm/core/signatures/utils.py
logillm/core/tools/__init__.py
logillm/core/tools/base.py
logillm/core/tools/registry.py
logillm/evaluate/__init__.py
logillm/evaluate/evaluator.py
logillm/evaluate/metrics.py
logillm/exceptions/__init__.py
logillm/exceptions/base.py
logillm/optimizers/__init__.py
logillm/optimizers/avatar_optimizer.py
logillm/optimizers/base.py
logillm/optimizers/bootstrap_fewshot.py
logillm/optimizers/copro.py
logillm/optimizers/demo_selectors.py
logillm/optimizers/format_adapter_base.py
logillm/optimizers/format_optimizer.py
logillm/optimizers/hybrid_optimizer.py
logillm/optimizers/hyperparameter.py
logillm/optimizers/instruction_optimizer.py
logillm-0.2.17.dist-info/METADATA
logillm-0.2.17.dist-info/WHEEL
logillm-0.2.17.dist-info/licenses/LICENSE
logillm-0.2.17.dist-info/RECORD
