Metadata-Version: 2.4
Name: logillm
Version: 0.2.17
Summary: A generic, high-performance, low-dependency LLM programming framework inspired by dspy
Project-URL: Homepage, https://github.com/mjbommar/logillm
Project-URL: Documentation, https://michaelbommarito.com/
Project-URL: Repository, https://github.com/mjbommar/logillm
Project-URL: Issues, https://github.com/mjbommar/logillm/issues
Author-email: Michael Bommarito <michael.bommarito@gmail.com>
License: MIT
License-File: LICENSE
Keywords: ai,dspy-inspired,language-models,llm,machine-learning,optimization,prompt-engineering
Classifier: Development Status :: 3 - Alpha
Classifier: Intended Audience :: Developers
Classifier: Intended Audience :: Science/Research
Classifier: License :: OSI Approved :: MIT License
Classifier: Operating System :: OS Independent
Classifier: Programming Language :: Python :: 3
Classifier: Programming Language :: Python :: 3.9
Classifier: Programming Language :: Python :: 3.10
Classifier: Programming Language :: Python :: 3.11
Classifier: Programming Language :: Python :: 3.12
Classifier: Programming Language :: Python :: 3.13
Classifier: Topic :: Scientific/Engineering :: Artificial Intelligence
Classifier: Topic :: Software Development :: Libraries :: Python Modules
Requires-Python: >=3.9
Requires-Dist: anthropic>=0.64.0
Requires-Dist: openai>=1.101.0
Provides-Extra: all
Requires-Dist: anthropic>=0.39.0; extra == 'all'
Requires-Dist: google-genai>=0.3.0; extra == 'all'
Requires-Dist: openai>=1.100.2; extra == 'all'
Provides-Extra: anthropic
Requires-Dist: anthropic>=0.39.0; extra == 'anthropic'
Provides-Extra: google
Requires-Dist: google-genai>=0.3.0; extra == 'google'
Provides-Extra: openai
Requires-Dist: openai>=1.100.2; extra == 'openai'
